LICENSE.md
README.md
setup.py
giraphics/__init__.py
giraphics.egg-info/PKG-INFO
giraphics.egg-info/SOURCES.txt
giraphics.egg-info/dependency_links.txt
giraphics.egg-info/requires.txt
giraphics.egg-info/top_level.txt
giraphics/animate/animation.py
giraphics/animate/animator.py
giraphics/animate/morphing_animation_test.py
giraphics/animate/movements.py
giraphics/graphing/Scenic.py
giraphics/graphing/fancygraph.py
giraphics/graphing/figure.py
giraphics/graphing/graph.py
giraphics/graphing/scenic2.py
giraphics/graphing3d/__init__.py
giraphics/graphing3d/graph3d.py
giraphics/graphing3d/graph3d2.py
giraphics/graphing3d/grapher3.py
giraphics/svg/__init__.py
giraphics/svg/morph.py
giraphics/svg/morph2.py
giraphics/svg/svgkit.py
giraphics/utilities/__init__.py
giraphics/utilities/caching_functions.py
giraphics/utilities/colour.py
giraphics/utilities/convert.py
giraphics/utilities/latex2.py
giraphics/utilities/latex_converter.py
giraphics/utilities/latex_svg_decoder.py
giraphics/utilities/latext.py
giraphics/utilities/mathtext.py
giraphics/utilities/parametrisations.py
giraphics/utilities/timer.py
giraphics/utilities/utils.py