Metadata-Version: 2.1
Name: giraphics
Version: 0.0.6
Summary: Lightweight graphing and animations
Home-page: https://github.com/tghira/giraphics
Author: T. G. Hiranandani
Author-email: giraphics@protonmail.com
License: MIT
Keywords: graphs,animations,graphics,vector-graphics
Classifier: Development Status :: 2 - Pre-Alpha
Classifier: Intended Audience :: Science/Research
Classifier: License :: OSI Approved :: MIT License
Classifier: Operating System :: OS Independent
Classifier: Programming Language :: Python :: 3.5
Classifier: Programming Language :: Python :: 3.6
Classifier: Programming Language :: Python :: 3.7
Classifier: Topic :: Scientific/Engineering :: Astronomy
Classifier: Topic :: Scientific/Engineering :: Physics
License-File: LICENSE.md
